ai_sidekick/__init__.py
ai_sidekick/main.py
ai_sidekick-0.1.1.dist-info/METADATA
ai_sidekick-0.1.1.dist-info/WHEEL
ai_sidekick-0.1.1.dist-info/entry_points.txt
ai_sidekick-0.1.1.dist-info/licenses/LICENSE
ai_sidekick-0.1.1.dist-info/RECORD
