Metadata-Version: 2.4
Name: ai-sidekick
Version: 0.1.1
Summary: Add your description here
Project-URL: Homepage, https://github.com/hesedcasa/ai-sidekick
Project-URL: Issues, https://github.com/hesedcasa/ai-sidekick/issues
Author-email: Hesed <support@hesed.casa>
License-Expression: Apache-2.0
License-File: LICENSE
Requires-Python: >=3.11
